upgrade/scripts/__init__.py
upgrade/scripts/exceptions.py
upgrade/scripts/find_compatible_versions.py
upgrade/scripts/manage_venv.py
upgrade/scripts/requirements.py
upgrade/scripts/slack.py
upgrade/scripts/upgrade_python_package.py
upgrade/scripts/utils.py
upgrade/scripts/validations.py
upgrade_python_package-0.8.1.dist-info/LICENSE
upgrade_python_package-0.8.1.dist-info/METADATA
upgrade_python_package-0.8.1.dist-info/WHEEL
upgrade_python_package-0.8.1.dist-info/entry_points.txt
upgrade_python_package-0.8.1.dist-info/top_level.txt
upgrade_python_package-0.8.1.dist-info/RECORD
