Metadata-Version: 2.2
Name: upgrade-python-package
Version: 0.8.1
Summary: A script for upgrading python packages
Home-page: https://github.com/openlawlibrary/upgrade-python-package
Author: Open Law Library
Author-email: info@openlawlib.org
Keywords: upgrade python package
Classifier: Development Status :: 2 - Pre-Alpha
Classifier: Intended Audience :: Developers
Classifier: Intended Audience :: Information Technology
Classifier: Topic :: Software Development :: Build Tools
Classifier: License :: OSI Approved :: Apache Software License
Classifier: Natural Language :: English
Classifier: Programming Language :: Python :: 3
Classifier: Programming Language :: Python :: 3.8
Classifier: Programming Language :: Python :: 3.9
Classifier: Programming Language :: Python :: 3.10
Classifier: Programming Language :: Python :: 3.11
Classifier: Programming Language :: Python :: 3.12
Classifier: Programming Language :: Python :: Implementation :: CPython
Classifier: Operating System :: OS Independent
License-File: LICENSE
Requires-Dist: lxml>=4.9
Requires-Dist: requests==2.*
Requires-Dist: packaging>=24.1
Provides-Extra: dev
Requires-Dist: wheel; extra == "dev"
Provides-Extra: test
Requires-Dist: flake8; extra == "test"
Requires-Dist: pytest; extra == "test"
Requires-Dist: mock; extra == "test"
Requires-Dist: setuptools; extra == "test"
